ossbom/__init__.py
ossbom/converters/__init__.py
ossbom/converters/cyclonedx_converter.py
ossbom/converters/factory.py
ossbom/converters/minibom_converter.py
ossbom/converters/test_factory.py
ossbom/model/__init__.py
ossbom/model/base.py
ossbom/model/component.py
ossbom/model/dependency_env.py
ossbom/model/environment.py
ossbom/model/minicomponent.py
ossbom/model/ossbom.py
ossbom/model/test_component.py
ossbom/model/test_environment.py
ossbom/model/test_minicomponent.py
ossbom/model/test_ossbom.py
ossbom/model/test_vulnerability.py
ossbom/model/vulnerability.py
ossbom/tests/__init__.py
ossbom/tests/test_utility.py
ossbom-1.0.10.dist-info/METADATA
ossbom-1.0.10.dist-info/WHEEL
ossbom-1.0.10.dist-info/RECORD
