Metadata-Version: 2.4
Name: ossbom
Version: 1.0.10
Summary: Main public API
Author: dreadnought
Requires-Python: >=3.12,<4.0
Classifier: Programming Language :: Python :: 3
Classifier: Programming Language :: Python :: 3.12
Classifier: Programming Language :: Python :: 3.13
Classifier: Programming Language :: Python :: 3.14
Requires-Dist: cyclonedx-python-lib[json-validation] (>=8.4.0,<9.0.0)
Requires-Dist: packageurl-python (>=0.16.0,<0.17.0)
Requires-Dist: poetry-plugin-export (>=1.9.0,<2.0.0)
